print_helper_logger/__init__.py
print_helper_logger/print_helper_logger.py
print_helper_logger-0.0.5.dist-info/LICENSE
print_helper_logger-0.0.5.dist-info/METADATA
print_helper_logger-0.0.5.dist-info/WHEEL
print_helper_logger-0.0.5.dist-info/top_level.txt
print_helper_logger-0.0.5.dist-info/RECORD
