Metadata-Version: 2.1
Name: print_helper_logger
Version: 0.0.5
Summary: Package for printing messages to the console and to the system logger
Home-page: https://github.com/oscargomezf/python_tools/print_helper_logger
Author: Oscar Gomez Fuente
Author-email: oscargomezf@gmail.com
License: MIT
Classifier: Programming Language :: Python :: 3
Classifier: License :: OSI Approved :: MIT License
Classifier: Operating System :: OS Independent
Requires-Python: >=3.6
License-File: LICENSE
